{
  "project_info": {
    "project_number": "468357672947",
    "project_id": "werkstuk-android-c4e4f",
    "storage_bucket": "werkstuk-android-c4e4f.appspot.com"
  },
  "client": [
    {
      "client_info": {
        "mobilesdk_app_id": "1:468357672947:android:3b0583b3437e4141662c86",
        "android_client_info": {
          "package_name": "com.example.werkstuk"
        }
      },
      "oauth_client": [
        {
          "client_id": "468357672947-pukht1ik2a7cp9f46ig20c51t7k89dnn.apps.googleusercontent.com",
          "client_type": 3
        }
      ],
      "api_key": [
        {
          "current_key": "AIzaSyAHzarotKOlyXmoM8Zs56R5eeqVucL8Qyo"
        }
      ],
      "services": {
        "appinvite_service": {
          "other_platform_oauth_client": [
            {
              "client_id": "468357672947-pukht1ik2a7cp9f46ig20c51t7k89dnn.apps.googleusercontent.com",
              "client_type": 3
            }
          ]
        }
      }
    }
  ],
  "configuration_version": "1"
}